[
  {
    "__TYPE__": "SharedSliceContent",
    "variation": "default",
    "primary": {
      "name": {
        "__TYPE__": "StructuredTextContent",
        "value": [
          {
            "type": "paragraph",
            "content": {
              "text": "Exercitation officia laborum veniam reprehenderit elit."
            }
          }
        ]
      },
      "link": {
        "__TYPE__": "LinkContent",
        "value": {
          "__TYPE__": "ExternalLink",
          "url": "https://slicemachine.dev"
        }
      }
    },
    "items": [
      {
        "__TYPE__": "GroupItemContent",
        "value": []
      }
    ]
  }
]